Metadata-Version: 1.0
Name: cache
Version: 1.0.0
Summary: caching for humans
Home-page: https://github.com/jayferd/python-cache
Author: Jay Adkisson
Author-email: j4yferd at gmail dot com (humans only, please)
License: MIT
Keywords: cache decorator humans
Platform: UNKNOWN
Classifier: Development Status :: 3 - Alpha
Classifier: Environment :: Web Environment
Classifier: Intended Audience :: Developers
Classifier: Topic :: Database :: Front-Ends
Classifier: License :: OSI Approved :: MIT License
